Workbook

Sheet Dashboard
A1: =" DASHBOARD MICROSOFT 365 - "&Config!$B$2 -> DASHBOARD MICROSOFT 365 - Target Tenant
A3: Entra | F3: Exchange | K3: SharePoint | P3: Teams | U3: Security
A5: Users | F5: Mailboxes | H5: Total size | K5: Site Collections | P5: Teams | U5: MFA Activated
A6: =COUNTIF(D_Users!$E$2:$E$20001,"Member") -> 0 | B6: Disabled | D6: =COUNTIFS(D_Users!$E$2:$E$20001,"Member",D_Users!$F$2:$F$20001,FALSE) -> 0 | F6: =COUNTA(D_Mailboxes!$A$2:$A$20001) -> 0 | H6: =ROUND(SUM(D_Mailboxes!$D$2:$D$20001),0)&" GB" -> 0 GB | K6: =COUNTIFS(D_SPOSites!$A$2:$A$10001,"<>",D_SPOSites!$H$2:$H$10001,FALSE) -> 0 | P6: =COUNTA(D_Teams!$A$2:$A$10001) -> 0 | R6: Public | S6: =COUNTIF(D_Teams!$C$2:$C$10001,"Public") -> 0 | U6: =COUNTIF(D_MFA!$B$2:$B$20001,TRUE) -> 0
B7: Licensed users | D7: =COUNTIFS(D_Users!$E$2:$E$20001,"Member",D_Users!$K$2:$K$20001,TRUE) -> 0 | R7: Private | S7: =COUNTIF(D_Teams!$C$2:$C$10001,"Private") -> 0
B8: Guest users | D8: =COUNTIF(D_Users!$E$2:$E$20001,"Guest") -> 0 | F8: Room | G8: =COUNTIF(D_Mailboxes!$C$2:$C$20001,"RoomMailbox")+COUNTIF(D_Mailboxes!$C$2:$C$20001,"EquipmentMailbox") -> 0 | K8: Storage used (GB) | M8: =ROUND(SUMIFS(D_SPOSites!$F$2:$F$10001,D_SPOSites!$H$2:$H$10001,FALSE),1) -> 0 | U8: Not registered
F9: Shared | G9: =COUNTIF(D_Mailboxes!$C$2:$C$20001,"SharedMailbox") -> 0 | K9: Inactive Sites | M9: =COUNTIFS(D_SPOSites!$A$2:$A$10001,"<>",D_SPOSites!$H$2:$H$10001,FALSE,D_SPOSites!$C$2:$C$10001,"<"&(Config!$B$11-Config!$B$5))+COUNTIFS(D_SPOSites!$A$2:$A$10001,"<>",D_SPOSites!$H$2:$H$10001,FALSE,D_SPOSites!$C$2:$C$10001,"=") -> 0 | P9: Channels | U9: =COUNTIFS(D_Users!$E$2:$E$20001,"Member",D_Users!$F$2:$F$20001,TRUE,D_Users!$K$2:$K$20001,TRUE,D_Users!$M$2:$M$20001,FALSE) -> 0
A10: Identity Types | C10: =IF(COUNTA(D_Users!$A$2:$A$20001)=0,"-",IF(COUNTIF(D_Users!$G$2:$G$20001,TRUE)=0,"Cloud-only","Hybrid ("&COUNTIF(D_Users!$G$2:$G$20001,TRUE)&" synced)")) -> - | F10: Users | G10: =COUNTIF(D_Mailboxes!$C$2:$C$20001,"UserMailbox") -> 0 | K10: Sharing External | M10: =IF(COUNTA(M_SPAdminSites!$A$2:$A$10001)=0,"manual",COUNTIFS(M_SPAdminSites!$E$2:$E$10001,"<>Team site",M_SPAdminSites!$I$2:$I$10001,"On")) -> manual | P10: =IF(COUNTA(M_TeamsAdminExport!$A$2:$A$10001)=0,"manual",SUM(M_TeamsAdminExport!$B$2:$D$10001)) -> manual | R10: Standard | S10: =IF(COUNTA(M_TeamsAdminExport!$A$2:$A$10001)=0,"manual",SUM(M_TeamsAdminExport!$B$2:$B$10001)) -> manual
F11: Groups | G11: =COUNTIF(D_Mailboxes!$C$2:$C$20001,"GroupMailbox")+COUNTIF(D_Mailboxes!$C$2:$C$20001,"TeamMailbox") -> 0 | R11: Private | S11: =IF(COUNTA(M_TeamsAdminExport!$A$2:$A$10001)=0,"manual",SUM(M_TeamsAdminExport!$C$2:$C$10001)) -> manual | U11: Security defaults | W11: =IF(D_SecuritySettings!$A$2="","-",IF(D_SecuritySettings!$A$2=TRUE,"Enabled","Disabled")) -> -
F12: Booking | G12: =COUNTIF(D_Mailboxes!$C$2:$C$20001,"SchedulingMailbox") -> 0 | R12: Shared | S12: =IF(COUNTA(M_TeamsAdminExport!$A$2:$A$10001)=0,"manual",SUM(M_TeamsAdminExport!$D$2:$D$10001)) -> manual | U12: Conditional Access | W12: =IF(D_SecuritySettings!$B$2="","-",D_SecuritySettings!$B$2&" ("&D_SecuritySettings!$C$2&" enabled)") -> -
A13: Groups | K13: Teams site | R13: Guests | S13: =IF(COUNTA(M_TeamsAdminExport!$A$2:$A$10001)=0,"manual",SUM(M_TeamsAdminExport!$G$2:$G$10001)) -> manual | U13: Password expire | W13: =IF(COUNT(D_Domains!$E$2:$E$301)=0,"-",IF(MIN(D_Domains!$E$2:$E$301)>=2147483647,"Never",MIN(D_Domains!$E$2:$E$301)&" days")) -> -
A14: =COUNTA(D_Groups!$B$2:$B$10001) -> 0 | B14: Security | D14: =COUNTIF(D_Groups!$D$2:$D$10001,"Security") -> 0 | F14: Mailboxes Activity* | K14: =COUNTIF(D_SPOSites!$H$2:$H$10001,TRUE) -> 0
B15: M365 | D15: =COUNTIF(D_Groups!$D$2:$D$10001,"Microsoft 365") -> 0 | F15: Very Active | H15: =COUNTIFS(D_Mailboxes!$C$2:$C$20001,"UserMailbox",D_Mailboxes!$F$2:$F$20001,">="&(Config!$B$11-Config!$B$3)) -> 0 | P15: Members | S15: =SUM(D_Teams!$D$2:$D$10001) -> 0 | U15: Role Assignments
F16: Active | H16: =COUNTIFS(D_Mailboxes!$C$2:$C$20001,"UserMailbox",D_Mailboxes!$F$2:$F$20001,">="&(Config!$B$11-Config!$B$4),D_Mailboxes!$F$2:$F$20001,"<"&(Config!$B$11-Config!$B$3)) -> 0 | K16: Storage used (GB) | M16: =ROUND(SUMIFS(D_SPOSites!$F$2:$F$10001,D_SPOSites!$H$2:$H$10001,TRUE),0) -> 0 | V16: Global Admin | X16: =COUNTIF(D_Roles!$A$2:$A$4001,"Global Administrator") -> 0
F17: Low Activity | H17: =COUNTIFS(D_Mailboxes!$C$2:$C$20001,"UserMailbox",D_Mailboxes!$F$2:$F$20001,">="&(Config!$B$11-Config!$B$5),D_Mailboxes!$F$2:$F$20001,"<"&(Config!$B$11-Config!$B$4)) -> 0 | K17: External sharing | M17: =IF(COUNTA(M_SPAdminSites!$A$2:$A$10001)=0,"manual",COUNTIFS(M_SPAdminSites!$E$2:$E$10001,"Team site",M_SPAdminSites!$I$2:$I$10001,"On")) -> manual | V17: SharePoint Admin | X17: =COUNTIF(D_Roles!$A$2:$A$4001,"SharePoint Administrator") -> 0
A18: Total number of devices | F18: Inactive | H18: =COUNTIF(D_Mailboxes!$C$2:$C$20001,"UserMailbox")-H15-H16-H17 -> 0 | V18: Teams Admin | X18: =COUNTIF(D_Roles!$A$2:$A$4001,"Teams Administrator") -> 0
A19: =COUNTA(D_DevicesEntra!$A$2:$A$20001) -> 0 | F19: Health Score** | H19: =IF(G10=0,"-",ROUND((H15+H16)/G10*100,1)&"%") -> - | K19: Very Active | M19: =COUNTIFS(D_SPOSites!$H$2:$H$10001,TRUE,D_SPOSites!$C$2:$C$10001,">="&(Config!$B$11-Config!$B$3)) -> 0 | V19: User Admin | X19: =COUNTIF(D_Roles!$A$2:$A$4001,"User Administrator") -> 0
F20: Mail Traffic - 1 Month | K20: Active | M20: =COUNTIFS(D_SPOSites!$H$2:$H$10001,TRUE,D_SPOSites!$C$2:$C$10001,">="&(Config!$B$11-Config!$B$4),D_SPOSites!$C$2:$C$10001,"<"&(Config!$B$11-Config!$B$3)) -> 0 | V20: Exchange Admin | X20: =COUNTIF(D_Roles!$A$2:$A$4001,"Exchange Administrator") -> 0
A21: =COUNTIFS(D_DevicesEntra!$E$2:$E$20001,">="&DATE(YEAR(Config!$B$11),1,1)) -> 0 | B21: =COUNTIFS(D_DevicesEntra!$E$2:$E$20001,"<"&(Config!$B$11-182))+COUNTIFS(D_DevicesEntra!$A$2:$A$20001,"<>",D_DevicesEntra!$E$2:$E$20001,"=") -> 0 | C21: =COUNTIF(D_DevicesIntune!$D$2:$D$20001,"noncompliant") -> 0 | D21: =COUNTIFS(D_DevicesEntra!$A$2:$A$20001,"<>",D_DevicesEntra!$G$2:$G$20001,FALSE) -> 0 | K21: Low Activity | M21: =COUNTIFS(D_SPOSites!$H$2:$H$10001,TRUE,D_SPOSites!$C$2:$C$10001,">="&(Config!$B$11-Config!$B$5),D_SPOSites!$C$2:$C$10001,"<"&(Config!$B$11-Config!$B$4)) -> 0 | V21: Total privileged | X21: =COUNTA(D_Roles!$A$2:$A$4001) -> 0
A22: Seen this year | B22: Stale > 6 months | C22: Non compliant | D22: Not Intune managed | K22: Inactive | M22: =K14-M19-M20-M21 -> 0
U23: Licenses & costs
A25: =IF(COUNTIF(M_MDE_Devices!$X$2:$X$20001,"Can be onboarded")>0,COUNTIF(M_MDE_Devices!$X$2:$X$20001,"Can be onboarded")&" devices discovered by MDE (unmanaged)","") | K25: Files | M25: =SUM(D_SPOSites!$D$2:$D$10001) -> 0 | U25: =IFERROR(INDEX(D_Licenses!$B$2:$B$301,MATCH(1,D_Licenses!$G$2:$G$301,0)),"") | W25: =IF($U25="","",INDEX(D_Licenses!$D$2:$D$301,MATCH(1,D_Licenses!$G$2:$G$301,0))) | X25: =IF($U25="","",IFERROR(VLOOKUP($U25,Config!$D$3:$E$103,2,FALSE),0))
A26: Enterprise applications | U26: =IFERROR(INDEX(D_Licenses!$B$2:$B$301,MATCH(2,D_Licenses!$G$2:$G$301,0)),"") | W26: =IF($U26="","",INDEX(D_Licenses!$D$2:$D$301,MATCH(2,D_Licenses!$G$2:$G$301,0))) | X26: =IF($U26="","",IFERROR(VLOOKUP($U26,Config!$D$3:$E$103,2,FALSE),0))
A27: =COUNTIFS(D_EnterpriseApps!$A$2:$A$5001,"<>",D_EnterpriseApps!$G$2:$G$5001,FALSE) -> 0 | K27: External Sharing | M27: =IF(D_SecuritySettings!$D$2="","-",IF(D_SecuritySettings!$D$2="Disabled","Disabled",IF(D_SecuritySettings!$D$2="ExistingExternalUserSharingOnly","Existing guests",IF(D_SecuritySettings!$D$2="ExternalUserSharingOnly","New and existing guests",IF(D_SecuritySettings!$D$2="ExternalUserAndGuestSharing","Anyone with link",D_SecuritySettings!$D$2))))) -> - | P27: OneDrive | U27: =IFERROR(INDEX(D_Licenses!$B$2:$B$301,MATCH(3,D_Licenses!$G$2:$G$301,0)),"") | W27: =IF($U27="","",INDEX(D_Licenses!$D$2:$D$301,MATCH(3,D_Licenses!$G$2:$G$301,0))) | X27: =IF($U27="","",IFERROR(VLOOKUP($U27,Config!$D$3:$E$103,2,FALSE),0))
U28: =IFERROR(INDEX(D_Licenses!$B$2:$B$301,MATCH(4,D_Licenses!$G$2:$G$301,0)),"") | W28: =IF($U28="","",INDEX(D_Licenses!$D$2:$D$301,MATCH(4,D_Licenses!$G$2:$G$301,0))) | X28: =IF($U28="","",IFERROR(VLOOKUP($U28,Config!$D$3:$E$103,2,FALSE),0))
A29: Applications Top 12 | F29: Send | G29: Receive | H29: Read | K29: Webpart | M29: =Config!$B$7 -> No | P29: Total Storage (GB) | R29: =ROUND(SUM(D_OneDrive!$F$2:$F$20001),0) -> 0 | U29: =IFERROR(INDEX(D_Licenses!$B$2:$B$301,MATCH(5,D_Licenses!$G$2:$G$301,0)),"") | W29: =IF($U29="","",INDEX(D_Licenses!$D$2:$D$301,MATCH(5,D_Licenses!$G$2:$G$301,0))) | X29: =IF($U29="","",IFERROR(VLOOKUP($U29,Config!$D$3:$E$103,2,FALSE),0))
F30: =SUM(D_EmailActivity!$B$2:$B$401) -> 0 | G30: =SUM(D_EmailActivity!$C$2:$C$401) -> 0 | H30: =SUM(D_EmailActivity!$D$2:$D$401) -> 0 | K30: Workflow | M30: =Config!$B$8 -> No | P30: Total account | R30: =COUNTA(D_OneDrive!$A$2:$A$20001) -> 0 | U30: =IFERROR(INDEX(D_Licenses!$B$2:$B$301,MATCH(6,D_Licenses!$G$2:$G$301,0)),"") | W30: =IF($U30="","",INDEX(D_Licenses!$D$2:$D$301,MATCH(6,D_Licenses!$G$2:$G$301,0))) | X30: =IF($U30="","",IFERROR(VLOOKUP($U30,Config!$D$3:$E$103,2,FALSE),0))
A31: =IFERROR(INDEX(D_EnterpriseApps!$A$2:$A$5001,MATCH(1,D_EnterpriseApps!$I$2:$I$5001,0)),"") | B31: =IFERROR(INDEX(D_EnterpriseApps!$A$2:$A$5001,MATCH(2,D_EnterpriseApps!$I$2:$I$5001,0)),"") | C31: =IFERROR(INDEX(D_EnterpriseApps!$A$2:$A$5001,MATCH(3,D_EnterpriseApps!$I$2:$I$5001,0)),"") | D31: =IFERROR(INDEX(D_EnterpriseApps!$A$2:$A$5001,MATCH(4,D_EnterpriseApps!$I$2:$I$5001,0)),"") | K31: Custom dev | M31: =Config!$B$9 -> No | U31: =IFERROR(INDEX(D_Licenses!$B$2:$B$301,MATCH(7,D_Licenses!$G$2:$G$301,0)),"") | W31: =IF($U31="","",INDEX(D_Licenses!$D$2:$D$301,MATCH(7,D_Licenses!$G$2:$G$301,0))) | X31: =IF($U31="","",IFERROR(VLOOKUP($U31,Config!$D$3:$E$103,2,FALSE),0))
A32: =IFERROR(INDEX(D_EnterpriseApps!$A$2:$A$5001,MATCH(5,D_EnterpriseApps!$I$2:$I$5001,0)),"") | B32: =IFERROR(INDEX(D_EnterpriseApps!$A$2:$A$5001,MATCH(6,D_EnterpriseApps!$I$2:$I$5001,0)),"") | C32: =IFERROR(INDEX(D_EnterpriseApps!$A$2:$A$5001,MATCH(7,D_EnterpriseApps!$I$2:$I$5001,0)),"") | D32: =IFERROR(INDEX(D_EnterpriseApps!$A$2:$A$5001,MATCH(8,D_EnterpriseApps!$I$2:$I$5001,0)),"") | F32: Distribution List | H32: =COUNTA(D_DistributionGroups!$A$2:$A$5001) -> 0 | P32: Files | Q32: =IF(SUM(D_OneDrive!$D$2:$D$20001)>=1000000,ROUND(SUM(D_OneDrive!$D$2:$D$20001)/1000000,1)&"M",SUM(D_OneDrive!$D$2:$D$20001)&"") -> 0 | U32: =IFERROR(INDEX(D_Licenses!$B$2:$B$301,MATCH(8,D_Licenses!$G$2:$G$301,0)),"") | W32: =IF($U32="","",INDEX(D_Licenses!$D$2:$D$301,MATCH(8,D_Licenses!$G$2:$G$301,0))) | X32: =IF($U32="","",IFERROR(VLOOKUP($U32,Config!$D$3:$E$103,2,FALSE),0))
A33: =IFERROR(INDEX(D_EnterpriseApps!$A$2:$A$5001,MATCH(9,D_EnterpriseApps!$I$2:$I$5001,0)),"") | B33: =IFERROR(INDEX(D_EnterpriseApps!$A$2:$A$5001,MATCH(10,D_EnterpriseApps!$I$2:$I$5001,0)),"") | C33: =IFERROR(INDEX(D_EnterpriseApps!$A$2:$A$5001,MATCH(11,D_EnterpriseApps!$I$2:$I$5001,0)),"") | D33: =IFERROR(INDEX(D_EnterpriseApps!$A$2:$A$5001,MATCH(12,D_EnterpriseApps!$I$2:$I$5001,0)),"") | F33: Archives | H33: =IF(COUNTIF(D_Mailboxes!$I$2:$I$20001,TRUE)>0,"Yes ("&COUNTIF(D_Mailboxes!$I$2:$I$20001,TRUE)&")","No") -> No | U33: Total Month | W33: =SUMPRODUCT(D_Licenses!$D$2:$D$301,D_Licenses!$F$2:$F$301) -> 0
F34: Number of domains | H34: =COUNTA(D_Domains!$A$2:$A$301) -> 0 | P34: External Sharing | R34: =IF(D_SecuritySettings!$D$2="","-",IF(D_SecuritySettings!$D$2="Disabled","Disabled",IF(D_SecuritySettings!$D$2="ExistingExternalUserSharingOnly","Existing guests",IF(D_SecuritySettings!$D$2="ExternalUserSharingOnly","New and existing guests",IF(D_SecuritySettings!$D$2="ExternalUserAndGuestSharing","Anyone with link",D_SecuritySettings!$D$2))))) -> - | U34: Total Year | W34: =W33*12 -> 0
F35: External forwarding | H35: =COUNTIF(D_Mailboxes!$M$2:$M$20001,TRUE) -> 0
A37: ="*Very Active: last user action ≤ "&Config!$B$3&" days (since "&TEXT(DAY(Config!$B$11-Config!$B$3),"00")&"/"&TEXT(MONTH(Config!$B$11-Config!$B$3),"00")&"/"&YEAR(Config!$B$11-Config!$B$3)&")" -> *Very Active: last user action ≤ 30 days (since 30/08/2026) | F37: Very Active | H37: =IF(COUNTIFS(D_Mailboxes!$C$2:$C$20001,"UserMailbox",D_Mailboxes!$H$2:$H$20001,"=")>0,"Review "&COUNTIFS(D_Mailboxes!$C$2:$C$20001,"UserMailbox",D_Mailboxes!$H$2:$H$20001,"=")&" mailboxes that never sent emails","")
A38: ="Active: last user action "&Config!$B$3+1&"-"&Config!$B$4&" days ago" -> Active: last user action 31-90 days ago | F38: Active | H38: =IF(H18>0,"Disable "&H18&" inactive mailboxes (> "&Config!$B$5&" days)","")
A39: ="Low Activity: last user action "&Config!$B$4+1&"-"&Config!$B$5&" days ago" -> Low Activity: last user action 91-180 days ago | F39: Low Activity | H39: =IF(H35>0,H35&" mailboxes forward email outside the tenant","")
A40: ="Inactive: last user action > "&Config!$B$5&" days ago, or never" -> Inactive: last user action > 180 days ago, or never | F40: Inactive | H40: =IF(COUNTIFS(D_MFA!$D$2:$D$20001,TRUE,D_MFA!$B$2:$B$20001,FALSE)>0,COUNTIFS(D_MFA!$D$2:$D$20001,TRUE,D_MFA!$B$2:$B$20001,FALSE)&" privileged accounts without MFA","")
H41: =IF(COUNTIFS(D_AppRegistrations!$E$2:$E$3001,">="&Config!$B$11,D_AppRegistrations!$E$2:$E$3001,"<"&(Config!$B$11+90))>0,COUNTIFS(D_AppRegistrations!$E$2:$E$3001,">="&Config!$B$11,D_AppRegistrations!$E$2:$E$3001,"<"&(Config!$B$11+90))&" app secrets expire within 90 days","")
A42: ="**("&H15&" + "&H16&") / "&G10&" = "&IF(G10=0,"-",ROUND((H15+H16)/G10*100,1)&"%")&" Healthy Active" -> **(0 + 0) / 0 = - Healthy Active

Sheet Config
A1: M365 AUDIT - CONFIGURATION | D1: License pricing - type unit price per month
A2: Tenant name | B2: Target Tenant | D2: FriendlyName | E2: UnitPrice/month
A3: Very Active threshold (days) | B3: 30 | D3: Azure Information Protection Premium P1
A4: Active threshold (days) | B4: 90 | D4: Copilot Studio Viral Trial
A5: Low Activity threshold (days) | B5: 180 | D5: Dynamics 365 Customer Service Enterprise
A6: Currency label | B6: EUR | D6: Dynamics 365 Customer Voice Trial
A7: Webpart used (Yes/No) - manual answer | B7: No | D7: Dynamics 365 Sales Enterprise
A8: Workflow used (Yes/No) - manual answer | B8: No | D8: Enterprise Mobility + Security E3
A9: Custom dev (Yes/No) - manual answer | B9: No | D9: Enterprise Mobility + Security E5
A10: Collect external file access (needs audit role, Yes/No) | B10: No | D10: Exchange Online (Plan 1)
A11: Reference date (run date, automatic) | B11: =IF(RunInfo!$B$4="",TODAY(),RunInfo!$B$4) -> 46294 | D11: Exchange Online (Plan 2)
A12: Deep mailbox scan (slow, Yes/No) | B12: No | D12: Exchange Online Archiving
D13: Exchange Online Kiosk
D14: Microsoft 365 Apps for business
D15: Microsoft 365 Apps for enterprise
D16: Microsoft 365 Audio Conferencing
D17: Microsoft 365 Business Basic
D18: Microsoft 365 Business Premium
D19: Microsoft 365 Business Standard
D20: Microsoft 365 Copilot
D21: Microsoft 365 E3
D22: Microsoft 365 E5
D23: Microsoft 365 E5 Developer
D24: Microsoft 365 F1
... D65: Windows Store for Business

Sheet RunInfo
A1: RUN INFO - filled by the importer
A3: Tenant name
A4: Run date
A5: Account
A6: Tenant id
A7: Concealed names in usage reports
A8: Warnings
A10: Dataset | B10: Rows | C10: Status | D10: Message

Sheet M_TeamsAdminExport
A1: Name | B1: Standard Channels | C1: Private Channels | D1: Shared Channels | E1: Team Members | F1: Owners | G1: Guests | H1: Privacy | I1: Status | J1: Classification | K1: Groups Id | L1: Expiration Date | M1: Description | N1: Sensitivity Label | P1: MANUAL INPUT - optional. Export from Teams admin center > Teams > Manage teams > Export. Save as TeamsAdminExport.csv in the MANUAL folder, or paste rows below.

Sheet M_SPAdminSites
A1: Site name | B1: URL | C1: Storage used (GB) | D1: Hub | E1: Template | F1: Last activity (UTC) | G1: Created by | H1: Files | I1: External sharing | K1: MANUAL INPUT - optional. Export from SharePoint admin center > Active sites > Export. Save as SPAdminSites.csv in the MANUAL folder, or paste rows below.

Sheet M_MDE_Devices
A1: Device ID | B1: Device Name | C1: Device Category | D1: Device Type | E1: Device Subtype | F1: Discovery sources | G1: Domain | H1: AAD Device Id | I1: First Seen | J1: Last device update | K1: OS Platform | L1: OS Distribution | M1: OS Version | N1: OS Build | O1: Windows 10 Version | P1: Tags | Q1: Group | R1: Is AAD Joined | S1: Device IPs | T1: Device MACs | U1: Risk Level | V1: Exposure Level | W1: Health Status | X1: Onboarding Status | Y1: Device Role | Z1: Cloud Platforms | AA1: Is Internet Facing | AB1: Enrollment Status Code | AC1: Managed By | AD1: Enrollment Status | AE1: Vendor | AF1: Model | AH1: MANUAL INPUT - optional. Export from security.microsoft.com > Assets > Devices > Export. Save as MDE_Devices.csv in the MANUAL folder, or paste rows below.

Sheet M_ExternalFileAccess
A1: Accessed Time | B1: External User | C1: Accessed File | D1: Site URL | E1: File Extension | F1: Workload | G1: More Info | I1: MANUAL INPUT - optional. Needs an account with an audit role (View-Only Audit Logs). Run Collect-M365Audit.ps1 with -IncludeExternalFileAccess, or drop ExternalFileAccess.csv in the MANUAL folder.

Sheet M_ITCosts
A1: Cost item | B1: Category | C1: Monthly cost | D1: Yearly cost | E1: Currency | F1: Comment | H1: MANUAL INPUT - optional. Free table for local IT costs (POS, SAP, firewall, internet...). Type rows directly or drop ITCosts.csv in the MANUAL folder.

Sheet D_Users
A1: Id | B1: DisplayName | C1: UserPrincipalName | D1: Mail | E1: UserType | F1: AccountEnabled | G1: OnPremSynced | H1: UsageLocation | I1: CreatedDateTime | J1: LicenseCount | K1: IsLicensed | M1: HasMfa (helper)
M2: =IF($A2="","",COUNTIFS(D_MFA!$A$2:$A$20001,$C2,D_MFA!$B$2:$B$20001,TRUE)>0)
M3: =IF($A3="","",COUNTIFS(D_MFA!$A$2:$A$20001,$C3,D_MFA!$B$2:$B$20001,TRUE)>0)
M4: =IF($A4="","",COUNTIFS(D_MFA!$A$2:$A$20001,$C4,D_MFA!$B$2:$B$20001,TRUE)>0)
M5: =IF($A5="","",COUNTIFS(D_MFA!$A$2:$A$20001,$C5,D_MFA!$B$2:$B$20001,TRUE)>0)
M6: =IF($A6="","",COUNTIFS(D_MFA!$A$2:$A$20001,$C6,D_MFA!$B$2:$B$20001,TRUE)>0)
M7: =IF($A7="","",COUNTIFS(D_MFA!$A$2:$A$20001,$C7,D_MFA!$B$2:$B$20001,TRUE)>0)
M8: =IF($A8="","",COUNTIFS(D_MFA!$A$2:$A$20001,$C8,D_MFA!$B$2:$B$20001,TRUE)>0)
M9: =IF($A9="","",COUNTIFS(D_MFA!$A$2:$A$20001,$C9,D_MFA!$B$2:$B$20001,TRUE)>0)
M10: =IF($A10="","",COUNTIFS(D_MFA!$A$2:$A$20001,$C10,D_MFA!$B$2:$B$20001,TRUE)>0)
M11: =IF($A11="","",COUNTIFS(D_MFA!$A$2:$A$20001,$C11,D_MFA!$B$2:$B$20001,TRUE)>0)
M12: =IF($A12="","",COUNTIFS(D_MFA!$A$2:$A$20001,$C12,D_MFA!$B$2:$B$20001,TRUE)>0)
M13: =IF($A13="","",COUNTIFS(D_MFA!$A$2:$A$20001,$C13,D_MFA!$B$2:$B$20001,TRUE)>0)
... M20001: =IF($A20001="","",COUNTIFS(D_MFA!$A$2:$A$20001,$C20001,D_MFA!$B$2:$B$20001,TRUE)>0)

Sheet D_Groups
A1: Id | B1: DisplayName | C1: Mail | D1: Category | E1: Visibility | F1: IsTeam

Sheet D_MFA
A1: UserPrincipalName | B1: IsMfaRegistered | C1: IsMfaCapable | D1: IsAdmin | E1: MethodsRegistered

Sheet D_Roles
A1: RoleName | B1: MemberDisplayName | C1: MemberUpn | D1: MemberType | E1: AssignmentType

Sheet D_EnterpriseApps
A1: DisplayName | B1: AppId | C1: PublisherName | D1: CreatedDateTime | E1: AccountEnabled | F1: Homepage | G1: IsMicrosoftFirstParty | I1: ThirdPartyRank (helper)
I2: =IF($A2="","",IF($G2<>FALSE,"",COUNTIFS($D$2:$D$5001,">"&$D2,$G$2:$G$5001,FALSE)+COUNTIFS($D$2:$D2,$D2,$G$2:$G2,FALSE)))
I3: =IF($A3="","",IF($G3<>FALSE,"",COUNTIFS($D$2:$D$5001,">"&$D3,$G$2:$G$5001,FALSE)+COUNTIFS($D$2:$D3,$D3,$G$2:$G3,FALSE)))
I4: =IF($A4="","",IF($G4<>FALSE,"",COUNTIFS($D$2:$D$5001,">"&$D4,$G$2:$G$5001,FALSE)+COUNTIFS($D$2:$D4,$D4,$G$2:$G4,FALSE)))
I5: =IF($A5="","",IF($G5<>FALSE,"",COUNTIFS($D$2:$D$5001,">"&$D5,$G$2:$G$5001,FALSE)+COUNTIFS($D$2:$D5,$D5,$G$2:$G5,FALSE)))
I6: =IF($A6="","",IF($G6<>FALSE,"",COUNTIFS($D$2:$D$5001,">"&$D6,$G$2:$G$5001,FALSE)+COUNTIFS($D$2:$D6,$D6,$G$2:$G6,FALSE)))
I7: =IF($A7="","",IF($G7<>FALSE,"",COUNTIFS($D$2:$D$5001,">"&$D7,$G$2:$G$5001,FALSE)+COUNTIFS($D$2:$D7,$D7,$G$2:$G7,FALSE)))
I8: =IF($A8="","",IF($G8<>FALSE,"",COUNTIFS($D$2:$D$5001,">"&$D8,$G$2:$G$5001,FALSE)+COUNTIFS($D$2:$D8,$D8,$G$2:$G8,FALSE)))
I9: =IF($A9="","",IF($G9<>FALSE,"",COUNTIFS($D$2:$D$5001,">"&$D9,$G$2:$G$5001,FALSE)+COUNTIFS($D$2:$D9,$D9,$G$2:$G9,FALSE)))
I10: =IF($A10="","",IF($G10<>FALSE,"",COUNTIFS($D$2:$D$5001,">"&$D10,$G$2:$G$5001,FALSE)+COUNTIFS($D$2:$D10,$D10,$G$2:$G10,FALSE)))
I11: =IF($A11="","",IF($G11<>FALSE,"",COUNTIFS($D$2:$D$5001,">"&$D11,$G$2:$G$5001,FALSE)+COUNTIFS($D$2:$D11,$D11,$G$2:$G11,FALSE)))
I12: =IF($A12="","",IF($G12<>FALSE,"",COUNTIFS($D$2:$D$5001,">"&$D12,$G$2:$G$5001,FALSE)+COUNTIFS($D$2:$D12,$D12,$G$2:$G12,FALSE)))
I13: =IF($A13="","",IF($G13<>FALSE,"",COUNTIFS($D$2:$D$5001,">"&$D13,$G$2:$G$5001,FALSE)+COUNTIFS($D$2:$D13,$D13,$G$2:$G13,FALSE)))
... I5001: =IF($A5001="","",IF($G5001<>FALSE,"",COUNTIFS($D$2:$D$5001,">"&$D5001,$G$2:$G$5001,FALSE)+COUNTIFS($D$2:$D5001,$D5001,$G$2:$G5001,FALSE)))

Sheet D_AppRegistrations
A1: DisplayName | B1: AppId | C1: CreatedDateTime | D1: SecretCount | E1: NearestSecretExpiry | F1: CertCount

Sheet D_Licenses
A1: SkuPartNumber | B1: FriendlyName | C1: Total | D1: Assigned | E1: Available | F1: UnitPrice (helper) | G1: AssignedRank (helper)
F2: =IF($B2="",0,IFERROR(VLOOKUP($B2,Config!$D$3:$E$103,2,FALSE),0)) -> 0 | G2: =IF($A2="","",IF(OR($D2="",$D2=0),"",COUNTIFS($D$2:$D$301,">"&$D2)+COUNTIF($D$2:$D2,$D2)))
F3: =IF($B3="",0,IFERROR(VLOOKUP($B3,Config!$D$3:$E$103,2,FALSE),0)) -> 0 | G3: =IF($A3="","",IF(OR($D3="",$D3=0),"",COUNTIFS($D$2:$D$301,">"&$D3)+COUNTIF($D$2:$D3,$D3)))
F4: =IF($B4="",0,IFERROR(VLOOKUP($B4,Config!$D$3:$E$103,2,FALSE),0)) -> 0 | G4: =IF($A4="","",IF(OR($D4="",$D4=0),"",COUNTIFS($D$2:$D$301,">"&$D4)+COUNTIF($D$2:$D4,$D4)))
F5: =IF($B5="",0,IFERROR(VLOOKUP($B5,Config!$D$3:$E$103,2,FALSE),0)) -> 0 | G5: =IF($A5="","",IF(OR($D5="",$D5=0),"",COUNTIFS($D$2:$D$301,">"&$D5)+COUNTIF($D$2:$D5,$D5)))
F6: =IF($B6="",0,IFERROR(VLOOKUP($B6,Config!$D$3:$E$103,2,FALSE),0)) -> 0 | G6: =IF($A6="","",IF(OR($D6="",$D6=0),"",COUNTIFS($D$2:$D$301,">"&$D6)+COUNTIF($D$2:$D6,$D6)))
F7: =IF($B7="",0,IFERROR(VLOOKUP($B7,Config!$D$3:$E$103,2,FALSE),0)) -> 0 | G7: =IF($A7="","",IF(OR($D7="",$D7=0),"",COUNTIFS($D$2:$D$301,">"&$D7)+COUNTIF($D$2:$D7,$D7)))
F8: =IF($B8="",0,IFERROR(VLOOKUP($B8,Config!$D$3:$E$103,2,FALSE),0)) -> 0 | G8: =IF($A8="","",IF(OR($D8="",$D8=0),"",COUNTIFS($D$2:$D$301,">"&$D8)+COUNTIF($D$2:$D8,$D8)))
F9: =IF($B9="",0,IFERROR(VLOOKUP($B9,Config!$D$3:$E$103,2,FALSE),0)) -> 0 | G9: =IF($A9="","",IF(OR($D9="",$D9=0),"",COUNTIFS($D$2:$D$301,">"&$D9)+COUNTIF($D$2:$D9,$D9)))
F10: =IF($B10="",0,IFERROR(VLOOKUP($B10,Config!$D$3:$E$103,2,FALSE),0)) -> 0 | G10: =IF($A10="","",IF(OR($D10="",$D10=0),"",COUNTIFS($D$2:$D$301,">"&$D10)+COUNTIF($D$2:$D10,$D10)))
F11: =IF($B11="",0,IFERROR(VLOOKUP($B11,Config!$D$3:$E$103,2,FALSE),0)) -> 0 | G11: =IF($A11="","",IF(OR($D11="",$D11=0),"",COUNTIFS($D$2:$D$301,">"&$D11)+COUNTIF($D$2:$D11,$D11)))
F12: =IF($B12="",0,IFERROR(VLOOKUP($B12,Config!$D$3:$E$103,2,FALSE),0)) -> 0 | G12: =IF($A12="","",IF(OR($D12="",$D12=0),"",COUNTIFS($D$2:$D$301,">"&$D12)+COUNTIF($D$2:$D12,$D12)))
F13: =IF($B13="",0,IFERROR(VLOOKUP($B13,Config!$D$3:$E$103,2,FALSE),0)) -> 0 | G13: =IF($A13="","",IF(OR($D13="",$D13=0),"",COUNTIFS($D$2:$D$301,">"&$D13)+COUNTIF($D$2:$D13,$D13)))
... F301: =IF($B301="",0,IFERROR(VLOOKUP($B301,Config!$D$3:$E$103,2,FALSE),0)) -> 0 | G301: =IF($A301="","",IF(OR($D301="",$D301=0),"",COUNTIFS($D$2:$D$301,">"&$D301)+COUNTIF($D$2:$D301,$D301)))

Sheet D_Mailboxes
A1: DisplayName | B1: PrimarySmtpAddress | C1: RecipientTypeDetails | D1: SizeGB | E1: ItemCount | F1: LastUserActionTime | G1: LastEmailReceived | H1: LastEmailSent | I1: ArchiveEnabled | J1: LitigationHold | K1: ForwardingSmtpAddress | L1: ForwardingAddress | M1: ForwardsExternally

Sheet D_MailboxPermissions
A1: Mailbox | B1: PermissionType | C1: Grantee

Sheet D_DistributionGroups
A1: DisplayName | B1: PrimarySmtpAddress | C1: Type | D1: MemberCountDirect

Sheet D_DLMembers
A1: DLName | B1: MemberDisplayName | C1: MemberSmtp | D1: MemberRecipientType

Sheet D_Domains
A1: DomainName | B1: Type | C1: IsDefault | D1: DkimEnabled | E1: PasswordValidityDays

Sheet D_TransportRules
A1: Name | B1: State | C1: Priority | D1: Comments

Sheet D_EmailActivity
A1: ReportDate | B1: Send | C1: Receive | D1: Read

Sheet D_EmailUserActivity
A1: UserPrincipalName | B1: LastActivityDate | C1: SendCount | D1: ReceiveCount | E1: ReadCount

Sheet D_SPOSites
A1: SiteUrl | B1: OwnerDisplayName | C1: LastActivityDate | D1: FileCount | E1: ActiveFileCount | F1: StorageUsedGB | G1: RootWebTemplate | H1: IsTeamsConnected

Sheet D_OneDrive
A1: OwnerUpn | B1: OwnerDisplayName | C1: LastActivityDate | D1: FileCount | E1: ActiveFileCount | F1: StorageUsedGB

Sheet D_Teams
A1: TeamName | B1: GroupId | C1: Visibility | D1: MemberCount | E1: ActiveUsers90d | F1: ChannelMessages90d | G1: LastActivityDate

Sheet D_TeamsUserActivity
A1: UserPrincipalName | B1: LastActivityDate | C1: TeamChatMessages | D1: PrivateChatMessages | E1: Calls | F1: Meetings

Sheet D_DevicesEntra
A1: DisplayName | B1: OS | C1: OSVersion | D1: TrustType | E1: LastSignIn | F1: IsCompliant | G1: IsManaged | H1: RegisteredDateTime

Sheet D_DevicesIntune
A1: DeviceName | B1: OS | C1: OSVersion | D1: ComplianceState | E1: LastSyncDateTime | F1: ManagementAgent | G1: Manufacturer | H1: Model | I1: EnrolledDateTime

Sheet D_SecuritySettings
A1: SecurityDefaultsEnabled | B1: CAPoliciesTotal | C1: CAPoliciesEnabled | D1: TenantSharingCapability | E1: SmtpAuthDisabled | F1: AuditEnabled
